<?xml version="1.0"?>
<WorldItems xmlns:xsd="http://www.w3.org/2001/XMLSchema" xmlns:xsi="http://www.w3.org/2001/XMLSchema-instance">
  <MapObjects>
    <SceneObjs>
      <name>Lowpoly_tree_sample (48)</name>
      <path />
      <position>
        <x>75.43283</x>
        <y>1.3</y>
        <z>-12.619915</z>
      </position>
      <rotation>
        <x>-0</x>
        <y>238.772842</y>
        <z>0</z>
      </rotation>
      <scale>
        <x>1</x>
        <y>1</y>
        <z>1</z>
      </scale>
      <tilePosition>
        <x>38</x>
        <y>0</y>
        <z>-29</z>
      </tilePosition>
      <coordinate>
        <x>2</x>
        <y>1</y>
      </coordinate>
      <type>ground</type>
    </SceneObjs>
    <SceneObjs>
      <name>Tree_lp_11</name>
      <path />
      <position>
        <x>75.04437</x>
        <y>-0.344218731</y>
        <z>-12.8554239</z>
      </position>
      <rotation>
        <x>270</x>
        <y>238.772827</y>
        <z>0</z>
      </rotation>
      <scale>
        <x>2</x>
        <y>2</y>
        <z>2</z>
      </scale>
      <tilePosition>
        <x>38</x>
        <y>0</y>
        <z>-29</z>
      </tilePosition>
      <coordinate>
        <x>2</x>
        <y>1</y>
      </coordinate>
      <type>ground</type>
    </SceneObjs>
    <SceneObjs>
      <name>Lowpoly_tree_sample (49)</name>
      <path />
      <position>
        <x>65.9165039</x>
        <y>1.3</y>
        <z>-15.8724957</z>
      </position>
      <rotation>
        <x>-0</x>
        <y>238.772842</y>
        <z>0</z>
      </rotation>
      <scale>
        <x>1</x>
        <y>1</y>
        <z>1</z>
      </scale>
      <tilePosition>
        <x>38</x>
        <y>0</y>
        <z>-29</z>
      </tilePosition>
      <coordinate>
        <x>2</x>
        <y>1</y>
      </coordinate>
      <type>ground</type>
    </SceneObjs>
    <SceneObjs>
      <name>Tree_lp_11</name>
      <path />
      <position>
        <x>65.5280457</x>
        <y>-0.344218731</y>
        <z>-16.1080055</z>
      </position>
      <rotation>
        <x>270</x>
        <y>238.772827</y>
        <z>0</z>
      </rotation>
      <scale>
        <x>2</x>
        <y>2</y>
        <z>2</z>
      </scale>
      <tilePosition>
        <x>38</x>
        <y>0</y>
        <z>-29</z>
      </tilePosition>
      <coordinate>
        <x>2</x>
        <y>1</y>
      </coordinate>
      <type>ground</type>
    </SceneObjs>
    <SceneObjs>
      <name>Lowpoly_tree_sample (50)</name>
      <path />
      <position>
        <x>44.80664</x>
        <y>1.3</y>
        <z>-3.91325378</z>
      </position>
      <rotation>
        <x>-0</x>
        <y>238.772842</y>
        <z>0</z>
      </rotation>
      <scale>
        <x>1</x>
        <y>1</y>
        <z>1</z>
      </scale>
      <tilePosition>
        <x>38</x>
        <y>0</y>
        <z>-29</z>
      </tilePosition>
      <coordinate>
        <x>2</x>
        <y>1</y>
      </coordinate>
      <type>ground</type>
    </SceneObjs>
    <SceneObjs>
      <name>Tree_lp_11</name>
      <path />
      <position>
        <x>44.4181862</x>
        <y>-0.344218731</y>
        <z>-4.148763</z>
      </position>
      <rotation>
        <x>270</x>
        <y>238.772827</y>
        <z>0</z>
      </rotation>
      <scale>
        <x>2</x>
        <y>2</y>
        <z>2</z>
      </scale>
      <tilePosition>
        <x>38</x>
        <y>0</y>
        <z>-29</z>
      </tilePosition>
      <coordinate>
        <x>2</x>
        <y>1</y>
      </coordinate>
      <type>ground</type>
    </SceneObjs>
    <SceneObjs>
      <name>Lowpoly_tree_sample (51)</name>
      <path />
      <position>
        <x>70.72335</x>
        <y>1.3</y>
        <z>-23.7657814</z>
      </position>
      <rotation>
        <x>-0</x>
        <y>238.772842</y>
        <z>0</z>
      </rotation>
      <scale>
        <x>1</x>
        <y>1</y>
        <z>1</z>
      </scale>
      <tilePosition>
        <x>38</x>
        <y>0</y>
        <z>-29</z>
      </tilePosition>
      <coordinate>
        <x>2</x>
        <y>1</y>
      </coordinate>
      <type>ground</type>
    </SceneObjs>
    <SceneObjs>
      <name>Tree_lp_11</name>
      <path />
      <position>
        <x>70.33489</x>
        <y>-0.344218731</y>
        <z>-24.0012913</z>
      </position>
      <rotation>
        <x>270</x>
        <y>238.772827</y>
        <z>0</z>
      </rotation>
      <scale>
        <x>2</x>
        <y>2</y>
        <z>2</z>
      </scale>
      <tilePosition>
        <x>38</x>
        <y>0</y>
        <z>-29</z>
      </tilePosition>
      <coordinate>
        <x>2</x>
        <y>1</y>
      </coordinate>
      <type>ground</type>
    </SceneObjs>
    <SceneObjs>
      <name>Lowpoly_tree_sample (53)</name>
      <path />
      <position>
        <x>60.74501</x>
        <y>1.3</y>
        <z>14.5383072</z>
      </position>
      <rotation>
        <x>-0</x>
        <y>238.772842</y>
        <z>0</z>
      </rotation>
      <scale>
        <x>1</x>
        <y>1</y>
        <z>1</z>
      </scale>
      <tilePosition>
        <x>38</x>
        <y>0</y>
        <z>-29</z>
      </tilePosition>
      <coordinate>
        <x>2</x>
        <y>1</y>
      </coordinate>
      <type>ground</type>
    </SceneObjs>
    <SceneObjs>
      <name>Tree_lp_11</name>
      <path />
      <position>
        <x>60.3565559</x>
        <y>-0.344218731</y>
        <z>14.3027983</z>
      </position>
      <rotation>
        <x>270</x>
        <y>238.772827</y>
        <z>0</z>
      </rotation>
      <scale>
        <x>2</x>
        <y>2</y>
        <z>2</z>
      </scale>
      <tilePosition>
        <x>38</x>
        <y>0</y>
        <z>-29</z>
      </tilePosition>
      <coordinate>
        <x>2</x>
        <y>1</y>
      </coordinate>
      <type>ground</type>
    </SceneObjs>
    <SceneObjs>
      <name>Lowpoly_tree_sample (54)</name>
      <path />
      <position>
        <x>51.228653</x>
        <y>1.3</y>
        <z>11.2856941</z>
      </position>
      <rotation>
        <x>-0</x>
        <y>238.772842</y>
        <z>0</z>
      </rotation>
      <scale>
        <x>1</x>
        <y>1</y>
        <z>1</z>
      </scale>
      <tilePosition>
        <x>38</x>
        <y>0</y>
        <z>-29</z>
      </tilePosition>
      <coordinate>
        <x>2</x>
        <y>1</y>
      </coordinate>
      <type>ground</type>
    </SceneObjs>
    <SceneObjs>
      <name>Tree_lp_11</name>
      <path />
      <position>
        <x>50.8402</x>
        <y>-0.344218731</y>
        <z>11.0501852</z>
      </position>
      <rotation>
        <x>270</x>
        <y>238.772827</y>
        <z>0</z>
      </rotation>
      <scale>
        <x>2</x>
        <y>2</y>
        <z>2</z>
      </scale>
      <tilePosition>
        <x>38</x>
        <y>0</y>
        <z>-29</z>
      </tilePosition>
      <coordinate>
        <x>2</x>
        <y>1</y>
      </coordinate>
      <type>ground</type>
    </SceneObjs>
    <SceneObjs>
      <name>Lowpoly_tree_sample (55)</name>
      <path />
      <position>
        <x>56.03553</x>
        <y>1.3</y>
        <z>3.39239883</z>
      </position>
      <rotation>
        <x>-0</x>
        <y>238.772842</y>
        <z>0</z>
      </rotation>
      <scale>
        <x>1</x>
        <y>1</y>
        <z>1</z>
      </scale>
      <tilePosition>
        <x>38</x>
        <y>0</y>
        <z>-29</z>
      </tilePosition>
      <coordinate>
        <x>2</x>
        <y>1</y>
      </coordinate>
      <type>ground</type>
    </SceneObjs>
    <SceneObjs>
      <name>Tree_lp_11</name>
      <path />
      <position>
        <x>55.6470757</x>
        <y>-0.344218731</y>
        <z>3.15688944</z>
      </position>
      <rotation>
        <x>270</x>
        <y>238.772827</y>
        <z>0</z>
      </rotation>
      <scale>
        <x>2</x>
        <y>2</y>
        <z>2</z>
      </scale>
      <tilePosition>
        <x>38</x>
        <y>0</y>
        <z>-29</z>
      </tilePosition>
      <coordinate>
        <x>2</x>
        <y>1</y>
      </coordinate>
      <type>ground</type>
    </SceneObjs>
    <SceneObjs>
      <name>Lowpoly_tree_sample (58)</name>
      <path />
      <position>
        <x>46.7193832</x>
        <y>1.3</y>
        <z>-26.1916466</z>
      </position>
      <rotation>
        <x>-0</x>
        <y>0.433439225</y>
        <z>-0</z>
      </rotation>
      <scale>
        <x>1</x>
        <y>1</y>
        <z>1</z>
      </scale>
      <tilePosition>
        <x>38</x>
        <y>0</y>
        <z>-29</z>
      </tilePosition>
      <coordinate>
        <x>2</x>
        <y>1</y>
      </coordinate>
      <type>ground</type>
    </SceneObjs>
    <SceneObjs>
      <name>Tree_lp_11</name>
      <path />
      <position>
        <x>46.72282</x>
        <y>-0.344218731</y>
        <z>-25.7373886</z>
      </position>
      <rotation>
        <x>270</x>
        <y>0.4334392</y>
        <z>0</z>
      </rotation>
      <scale>
        <x>2</x>
        <y>2</y>
        <z>2</z>
      </scale>
      <tilePosition>
        <x>38</x>
        <y>0</y>
        <z>-29</z>
      </tilePosition>
      <coordinate>
        <x>2</x>
        <y>1</y>
      </coordinate>
      <type>ground</type>
    </SceneObjs>
    <SceneObjs>
      <name>Lowpoly_tree_sample (143)</name>
      <path />
      <position>
        <x>108.280464</x>
        <y>1.30000019</y>
        <z>13.8392849</z>
      </position>
      <rotation>
        <x>-0</x>
        <y>337.750916</y>
        <z>0</z>
      </rotation>
      <scale>
        <x>1</x>
        <y>1</y>
        <z>1</z>
      </scale>
      <tilePosition>
        <x>38</x>
        <y>0</y>
        <z>-29</z>
      </tilePosition>
      <coordinate>
        <x>2</x>
        <y>1</y>
      </coordinate>
      <type>ground</type>
    </SceneObjs>
    <SceneObjs>
      <name>Tree_lp_11</name>
      <path />
      <position>
        <x>108.108459</x>
        <y>-0.3442185</y>
        <z>14.2597342</z>
      </position>
      <rotation>
        <x>270</x>
        <y>337.750916</y>
        <z>0</z>
      </rotation>
      <scale>
        <x>2</x>
        <y>2</y>
        <z>2</z>
      </scale>
      <tilePosition>
        <x>38</x>
        <y>0</y>
        <z>-29</z>
      </tilePosition>
      <coordinate>
        <x>2</x>
        <y>1</y>
      </coordinate>
      <type>ground</type>
    </SceneObjs>
    <SceneObjs>
      <name>Lowpoly_tree_sample (144)</name>
      <path />
      <position>
        <x>106.552788</x>
        <y>1.30000019</y>
        <z>23.746624</z>
      </position>
      <rotation>
        <x>-0</x>
        <y>337.750916</y>
        <z>0</z>
      </rotation>
      <scale>
        <x>1</x>
        <y>1</y>
        <z>1</z>
      </scale>
      <tilePosition>
        <x>38</x>
        <y>0</y>
        <z>-29</z>
      </tilePosition>
      <coordinate>
        <x>2</x>
        <y>1</y>
      </coordinate>
      <type>ground</type>
    </SceneObjs>
    <SceneObjs>
      <name>Tree_lp_11</name>
      <path />
      <position>
        <x>106.380783</x>
        <y>-0.3442185</y>
        <z>24.1670742</z>
      </position>
      <rotation>
        <x>270</x>
        <y>337.750916</y>
        <z>0</z>
      </rotation>
      <scale>
        <x>2</x>
        <y>2</y>
        <z>2</z>
      </scale>
      <tilePosition>
        <x>38</x>
        <y>0</y>
        <z>-29</z>
      </tilePosition>
      <coordinate>
        <x>2</x>
        <y>1</y>
      </coordinate>
      <type>ground</type>
    </SceneObjs>
    <SceneObjs>
      <name>Lowpoly_tree_sample (146)</name>
      <path />
      <position>
        <x>98.00614</x>
        <y>1.30000019</y>
        <z>20.2304344</z>
      </position>
      <rotation>
        <x>-0</x>
        <y>337.750916</y>
        <z>0</z>
      </rotation>
      <scale>
        <x>1</x>
        <y>1</y>
        <z>1</z>
      </scale>
      <tilePosition>
        <x>38</x>
        <y>0</y>
        <z>-29</z>
      </tilePosition>
      <coordinate>
        <x>2</x>
        <y>1</y>
      </coordinate>
      <type>ground</type>
    </SceneObjs>
    <SceneObjs>
      <name>Tree_lp_11</name>
      <path />
      <position>
        <x>97.83414</x>
        <y>-0.3442185</y>
        <z>20.6508846</z>
      </position>
      <rotation>
        <x>270</x>
        <y>337.750916</y>
        <z>0</z>
      </rotation>
      <scale>
        <x>2</x>
        <y>2</y>
        <z>2</z>
      </scale>
      <tilePosition>
        <x>38</x>
        <y>0</y>
        <z>-29</z>
      </tilePosition>
      <coordinate>
        <x>2</x>
        <y>1</y>
      </coordinate>
      <type>ground</type>
    </SceneObjs>
    <SceneObjs>
      <name>Lowpoly_tree_sample (147)</name>
      <path />
      <position>
        <x>92.542305</x>
        <y>1.30000019</y>
        <z>32.46194</z>
      </position>
      <rotation>
        <x>-0</x>
        <y>337.750916</y>
        <z>0</z>
      </rotation>
      <scale>
        <x>1</x>
        <y>1</y>
        <z>1</z>
      </scale>
      <tilePosition>
        <x>38</x>
        <y>0</y>
        <z>-29</z>
      </tilePosition>
      <coordinate>
        <x>2</x>
        <y>1</y>
      </coordinate>
      <type>ground</type>
    </SceneObjs>
    <SceneObjs>
      <name>Tree_lp_11</name>
      <path />
      <position>
        <x>92.3703</x>
        <y>-0.3442185</y>
        <z>32.88239</z>
      </position>
      <rotation>
        <x>270</x>
        <y>337.750916</y>
        <z>0</z>
      </rotation>
      <scale>
        <x>2</x>
        <y>2</y>
        <z>2</z>
      </scale>
      <tilePosition>
        <x>38</x>
        <y>0</y>
        <z>-29</z>
      </tilePosition>
      <coordinate>
        <x>2</x>
        <y>1</y>
      </coordinate>
      <type>ground</type>
    </SceneObjs>
    <SceneObjs>
      <name>Lowpoly_tree_sample (152)</name>
      <path />
      <position>
        <x>90.01623</x>
        <y>1.30000019</y>
        <z>48.04875</z>
      </position>
      <rotation>
        <x>-0</x>
        <y>99.4115753</y>
        <z>-0</z>
      </rotation>
      <scale>
        <x>1</x>
        <y>1</y>
        <z>1</z>
      </scale>
      <tilePosition>
        <x>38</x>
        <y>0</y>
        <z>-29</z>
      </tilePosition>
      <coordinate>
        <x>2</x>
        <y>1</y>
      </coordinate>
      <type>ground</type>
    </SceneObjs>
    <SceneObjs>
      <name>Tree_lp_11</name>
      <path />
      <position>
        <x>90.464386</x>
        <y>-0.3442185</y>
        <z>47.97447</z>
      </position>
      <rotation>
        <x>270</x>
        <y>99.4115753</y>
        <z>0</z>
      </rotation>
      <scale>
        <x>2</x>
        <y>2</y>
        <z>2</z>
      </scale>
      <tilePosition>
        <x>38</x>
        <y>0</y>
        <z>-29</z>
      </tilePosition>
      <coordinate>
        <x>2</x>
        <y>1</y>
      </coordinate>
      <type>ground</type>
    </SceneObjs>
    <SceneObjs>
      <name>Lowpoly_tree_sample (153)</name>
      <path />
      <position>
        <x>99.3559</x>
        <y>1.30000019</y>
        <z>44.3189926</z>
      </position>
      <rotation>
        <x>-0</x>
        <y>99.4115753</y>
        <z>-0</z>
      </rotation>
      <scale>
        <x>1</x>
        <y>1</y>
        <z>1</z>
      </scale>
      <tilePosition>
        <x>38</x>
        <y>0</y>
        <z>-29</z>
      </tilePosition>
      <coordinate>
        <x>2</x>
        <y>1</y>
      </coordinate>
      <type>ground</type>
    </SceneObjs>
    <SceneObjs>
      <name>Tree_lp_11</name>
      <path />
      <position>
        <x>99.80406</x>
        <y>-0.3442185</y>
        <z>44.24471</z>
      </position>
      <rotation>
        <x>270</x>
        <y>99.4115753</y>
        <z>0</z>
      </rotation>
      <scale>
        <x>2</x>
        <y>2</y>
        <z>2</z>
      </scale>
      <tilePosition>
        <x>38</x>
        <y>0</y>
        <z>-29</z>
      </tilePosition>
      <coordinate>
        <x>2</x>
        <y>1</y>
      </coordinate>
      <type>ground</type>
    </SceneObjs>
    <SceneObjs>
      <name>Obstacle1 (1)</name>
      <path />
      <position>
        <x>40.08</x>
        <y>0</y>
        <z>0</z>
      </position>
      <rotation>
        <x>-0</x>
        <y>270.538</y>
        <z>0</z>
      </rotation>
      <scale>
        <x>1</x>
        <y>1</y>
        <z>1</z>
      </scale>
      <tilePosition>
        <x>38</x>
        <y>0</y>
        <z>-29</z>
      </tilePosition>
      <coordinate>
        <x>2</x>
        <y>1</y>
      </coordinate>
      <type>obstacle</type>
    </SceneObjs>
    <SceneObjs>
      <name>Cube</name>
      <path />
      <position>
        <x>40.08</x>
        <y>0</y>
        <z>0</z>
      </position>
      <rotation>
        <x>-0</x>
        <y>270.538</y>
        <z>0</z>
      </rotation>
      <scale>
        <x>10</x>
        <y>10</y>
        <z>1</z>
      </scale>
      <tilePosition>
        <x>38</x>
        <y>0</y>
        <z>-29</z>
      </tilePosition>
      <coordinate>
        <x>2</x>
        <y>1</y>
      </coordinate>
      <type>obstacle</type>
    </SceneObjs>
    <SceneObjs>
      <name>Obstacle1 (2)</name>
      <path />
      <position>
        <x>39.95</x>
        <y>0</y>
        <z>-14.04</z>
      </position>
      <rotation>
        <x>-0</x>
        <y>270.538</y>
        <z>0</z>
      </rotation>
      <scale>
        <x>1</x>
        <y>1</y>
        <z>1</z>
      </scale>
      <tilePosition>
        <x>38</x>
        <y>0</y>
        <z>-29</z>
      </tilePosition>
      <coordinate>
        <x>2</x>
        <y>1</y>
      </coordinate>
      <type>obstacle</type>
    </SceneObjs>
    <SceneObjs>
      <name>Cube</name>
      <path />
      <position>
        <x>39.95</x>
        <y>0</y>
        <z>-14.04</z>
      </position>
      <rotation>
        <x>-0</x>
        <y>270.538</y>
        <z>0</z>
      </rotation>
      <scale>
        <x>10</x>
        <y>10</y>
        <z>1</z>
      </scale>
      <tilePosition>
        <x>38</x>
        <y>0</y>
        <z>-29</z>
      </tilePosition>
      <coordinate>
        <x>2</x>
        <y>1</y>
      </coordinate>
      <type>obstacle</type>
    </SceneObjs>
    <SceneObjs>
      <name>Obstacle1 (3)</name>
      <path />
      <position>
        <x>39.81</x>
        <y>0</y>
        <z>-28.99</z>
      </position>
      <rotation>
        <x>-0</x>
        <y>270.538</y>
        <z>0</z>
      </rotation>
      <scale>
        <x>1</x>
        <y>1</y>
        <z>1</z>
      </scale>
      <tilePosition>
        <x>38</x>
        <y>0</y>
        <z>-29</z>
      </tilePosition>
      <coordinate>
        <x>2</x>
        <y>1</y>
      </coordinate>
      <type>obstacle</type>
    </SceneObjs>
    <SceneObjs>
      <name>Cube</name>
      <path />
      <position>
        <x>39.81</x>
        <y>0</y>
        <z>-28.99</z>
      </position>
      <rotation>
        <x>-0</x>
        <y>270.538</y>
        <z>0</z>
      </rotation>
      <scale>
        <x>10</x>
        <y>10</y>
        <z>1</z>
      </scale>
      <tilePosition>
        <x>38</x>
        <y>0</y>
        <z>-29</z>
      </tilePosition>
      <coordinate>
        <x>2</x>
        <y>1</y>
      </coordinate>
      <type>obstacle</type>
    </SceneObjs>
    <SceneObjs>
      <name>Obstacle2 (6)</name>
      <path />
      <position>
        <x>104.376976</x>
        <y>1.52587891E-05</y>
        <z>-7.30122757</z>
      </position>
      <rotation>
        <x>-0</x>
        <y>43.7540627</y>
        <z>-0</z>
      </rotation>
      <scale>
        <x>1</x>
        <y>1</y>
        <z>1</z>
      </scale>
      <tilePosition>
        <x>38</x>
        <y>0</y>
        <z>-29</z>
      </tilePosition>
      <coordinate>
        <x>2</x>
        <y>1</y>
      </coordinate>
      <type>obstacle</type>
    </SceneObjs>
    <SceneObjs>
      <name>Cube</name>
      <path />
      <position>
        <x>104.376976</x>
        <y>5.00001526</y>
        <z>-7.30122757</z>
      </position>
      <rotation>
        <x>-0</x>
        <y>43.7540627</y>
        <z>-0</z>
      </rotation>
      <scale>
        <x>10</x>
        <y>10</y>
        <z>2</z>
      </scale>
      <tilePosition>
        <x>38</x>
        <y>0</y>
        <z>-29</z>
      </tilePosition>
      <coordinate>
        <x>2</x>
        <y>1</y>
      </coordinate>
      <type>obstacle</type>
    </SceneObjs>
  </MapObjects>
</WorldItems>